LICENSE
MANIFEST.in
README.md
requirements.txt
setup.py
pytimelib/__init__.py
pytimelib/__version__.py
pytimelib/timelib.py
pytimelib.egg-info/PKG-INFO
pytimelib.egg-info/SOURCES.txt
pytimelib.egg-info/dependency_links.txt
pytimelib.egg-info/requires.txt
pytimelib.egg-info/top_level.txt
test/test.py