Metadata-Version: 2.1
Name: pytimelib
Version: 1.0.2
Summary: pytimelib is a simple model for python to do time conversion.
Home-page: https://github.com/Geoge-Henry/timelib-py
Author: henry_czh
Author-email: henry_czh@foxmail.com
License: UNKNOWN
Platform: UNKNOWN
